<?xml version="1.0" encoding="UTF-8" standalone="no"?>
<menu>
<game name="Armor Battle (Mattel Electronics)" index="true" image="a">
	<description>Armor Battle (Mattel Electronics)</description>
	<cloneof></cloneof>
	<crc></crc>
	<manufacturer></manufacturer>
	<year></year>
	<genre></genre>
	<rating></rating>
	<enabled>Yes</enabled>
</game>
<game name="Banana (VTech, Time &amp; Fun)" index="true" image="b">
	<description>Banana (VTech, Time &amp; Fun)</description>
	<cloneof></cloneof>
	<crc></crc>
	<manufacturer></manufacturer>
	<year></year>
	<genre></genre>
	<rating></rating>
	<enabled>Yes</enabled>
</game>
<game name="Baseball (VTech, Explorer Time &amp; Fun)" index="" image="">
	<description>Baseball (VTech, Explorer Time &amp; Fun)</description>
	<cloneof></cloneof>
	<crc></crc>
	<manufacturer></manufacturer>
	<year></year>
	<genre></genre>
	<rating></rating>
	<enabled>Yes</enabled>
</game>
<game name="Bomb Fight (VTech, Mini Time &amp; Fun)" index="" image="">
	<description>Bomb Fight (VTech, Mini Time &amp; Fun)</description>
	<cloneof></cloneof>
	<crc></crc>
	<manufacturer></manufacturer>
	<year></year>
	<genre></genre>
	<rating></rating>
	<enabled>Yes</enabled>
</game>
<game name="Caccia al Ladro (VTech, Mini Time &amp; Fun)" index="true" image="c">
	<description>Caccia al Ladro (VTech, Mini Time &amp; Fun)</description>
	<cloneof></cloneof>
	<crc></crc>
	<manufacturer></manufacturer>
	<year></year>
	<genre></genre>
	<rating></rating>
	<enabled>Yes</enabled>
</game>
<game name="Cessate il Fuoco (VTech, Mini Time &amp; Fun)" index="" image="">
	<description>Cessate il Fuoco (VTech, Mini Time &amp; Fun)</description>
	<cloneof></cloneof>
	<crc></crc>
	<manufacturer></manufacturer>
	<year></year>
	<genre></genre>
	<rating></rating>
	<enabled>Yes</enabled>
</game>
<game name="Chicky Woggy (VTech, Arcade Time &amp; Fun)" index="" image="">
	<description>Chicky Woggy (VTech, Arcade Time &amp; Fun)</description>
	<cloneof></cloneof>
	<crc></crc>
	<manufacturer></manufacturer>
	<year></year>
	<genre></genre>
	<rating></rating>
	<enabled>Yes</enabled>
</game>
<game name="Chicky Woggy (VTech, Electronic Tini-Arcade)" index="" image="">
	<description>Chicky Woggy (VTech, Electronic Tini-Arcade)</description>
	<cloneof></cloneof>
	<crc></crc>
	<manufacturer></manufacturer>
	<year></year>
	<genre></genre>
	<rating></rating>
	<enabled>Yes</enabled>
</game>
<game name="Condor (VTech, Time &amp; Fun)" index="" image="">
	<description>Condor (VTech, Time &amp; Fun)</description>
	<cloneof></cloneof>
	<crc></crc>
	<manufacturer></manufacturer>
	<year></year>
	<genre></genre>
	<rating></rating>
	<enabled>Yes</enabled>
</game>
<game name="Crazy Chewy (VTech, Electronic Tini-Arcade)" index="" image="">
	<description>Crazy Chewy (VTech, Electronic Tini-Arcade)</description>
	<cloneof></cloneof>
	<crc></crc>
	<manufacturer></manufacturer>
	<year></year>
	<genre></genre>
	<rating></rating>
	<enabled>Yes</enabled>
</game>
<game name="Defendo (VTech, Explorer Time &amp; Fun)" index="true" image="d">
	<description>Defendo (VTech, Explorer Time &amp; Fun)</description>
	<cloneof></cloneof>
	<crc></crc>
	<manufacturer></manufacturer>
	<year></year>
	<genre></genre>
	<rating></rating>
	<enabled>Yes</enabled>
</game>
<game name="Donkey Kong (Coleco)" index="" image="">
	<description>Donkey Kong (Coleco)</description>
	<cloneof></cloneof>
	<crc></crc>
	<manufacturer></manufacturer>
	<year></year>
	<genre></genre>
	<rating></rating>
	<enabled>Yes</enabled>
</game>
<game name="Donkey Kong (Nintendo, Multi Screen)" index="" image="">
	<description>Donkey Kong (Nintendo, Multi Screen)</description>
	<cloneof></cloneof>
	<crc></crc>
	<manufacturer></manufacturer>
	<year></year>
	<genre></genre>
	<rating></rating>
	<enabled>Yes</enabled>
</game>
<game name="Donkey Kong II (Nintendo, Multi Screen)" index="" image="">
	<description>Donkey Kong II (Nintendo, Multi Screen)</description>
	<cloneof></cloneof>
	<crc></crc>
	<manufacturer></manufacturer>
	<year></year>
	<genre></genre>
	<rating></rating>
	<enabled>Yes</enabled>
</game>
<game name="Donkey Kong Jr. (Coleco)" index="" image="">
	<description>Donkey Kong Jr. (Coleco)</description>
	<cloneof></cloneof>
	<crc></crc>
	<manufacturer></manufacturer>
	<year></year>
	<genre></genre>
	<rating></rating>
	<enabled>Yes</enabled>
</game>
<game name="Donkey Kong Jr. (Nintendo, Table Top)" index="" image="">
	<description>Donkey Kong Jr. (Nintendo, Table Top)</description>
	<cloneof></cloneof>
	<crc></crc>
	<manufacturer></manufacturer>
	<year></year>
	<genre></genre>
	<rating></rating>
	<enabled>Yes</enabled>
</game>
<game name="Dungeons &amp; Dragons Computer Fantasy Game (Mattel Electronics, Arcade Action Series)" index="" image="">
	<description>Dungeons &amp; Dragons Computer Fantasy Game (Mattel Electronics, Arcade Action Series)</description>
	<cloneof></cloneof>
	<crc></crc>
	<manufacturer></manufacturer>
	<year></year>
	<genre></genre>
	<rating></rating>
	<enabled>Yes</enabled>
</game>
<game name="Egg (Nintendo, Wide Screen)" index="true" image="e">
	<description>Egg (Nintendo, Wide Screen)</description>
	<cloneof></cloneof>
	<crc></crc>
	<manufacturer></manufacturer>
	<year></year>
	<genre></genre>
	<rating></rating>
	<enabled>Yes</enabled>
</game>
<game name="Engine Room (VTech, Explorer Time &amp; Fun)" index="" image="">
	<description>Engine Room (VTech, Explorer Time &amp; Fun)</description>
	<cloneof></cloneof>
	<crc></crc>
	<manufacturer></manufacturer>
	<year></year>
	<genre></genre>
	<rating></rating>
	<enabled>Yes</enabled>
</game>
<game name="Escape (VTech, Time &amp; Fun)" index="" image="">
	<description>Escape (VTech, Time &amp; Fun)</description>
	<cloneof></cloneof>
	<crc></crc>
	<manufacturer></manufacturer>
	<year></year>
	<genre></genre>
	<rating></rating>
	<enabled>Yes</enabled>
</game>
<game name="Explorers of Space (Elektronika)" index="" image="">
	<description>Explorers of Space (Elektronika)</description>
	<cloneof></cloneof>
	<crc></crc>
	<manufacturer></manufacturer>
	<year></year>
	<genre></genre>
	<rating></rating>
	<enabled>Yes</enabled>
</game>
<game name="Fowling (Elektronika)" index="true" image="f">
	<description>Fowling (Elektronika)</description>
	<cloneof></cloneof>
	<crc></crc>
	<manufacturer></manufacturer>
	<year></year>
	<genre></genre>
	<rating></rating>
	<enabled>Yes</enabled>
</game>
<game name="Frog Boaster (Elektronika)" index="" image="">
	<description>Frog Boaster (Elektronika)</description>
	<cloneof></cloneof>
	<crc></crc>
	<manufacturer></manufacturer>
	<year></year>
	<genre></genre>
	<rating></rating>
	<enabled>Yes</enabled>
</game>
<game name="Galaxy II (Epoch)" index="true" image="g">
	<description>Galaxy II (Epoch)</description>
	<cloneof></cloneof>
	<crc></crc>
	<manufacturer></manufacturer>
	<year></year>
	<genre></genre>
	<rating></rating>
	<enabled>Yes</enabled>
</game>
<game name="Grab Man (unknown manufacturer, Game &amp; Time)" index="" image="">
	<description>Grab Man (unknown manufacturer, Game &amp; Time)</description>
	<cloneof></cloneof>
	<crc></crc>
	<manufacturer></manufacturer>
	<year></year>
	<genre></genre>
	<rating></rating>
	<enabled>Yes</enabled>
</game>
<game name="Hippo Teeth (VTech, Mini Time &amp; Fun)" index="true" image="h">
	<description>Hippo Teeth (VTech, Mini Time &amp; Fun)</description>
	<cloneof></cloneof>
	<crc></crc>
	<manufacturer></manufacturer>
	<year></year>
	<genre></genre>
	<rating></rating>
	<enabled>Yes</enabled>
</game>
<game name="Hippo Teeth (VTech, Sporty Time &amp; Fun)" index="" image="">
	<description>Hippo Teeth (VTech, Sporty Time &amp; Fun)</description>
	<cloneof></cloneof>
	<crc></crc>
	<manufacturer></manufacturer>
	<year></year>
	<genre></genre>
	<rating></rating>
	<enabled>Yes</enabled>
</game>
<game name="Hot Line (VTech, Mini Time &amp; Fun)" index="" image="">
	<description>Hot Line (VTech, Mini Time &amp; Fun)</description>
	<cloneof></cloneof>
	<crc></crc>
	<manufacturer></manufacturer>
	<year></year>
	<genre></genre>
	<rating></rating>
	<enabled>Yes</enabled>
</game>
<game name="Hot Line (VTech, Sporty Time &amp; Fun)" index="" image="">
	<description>Hot Line (VTech, Sporty Time &amp; Fun)</description>
	<cloneof></cloneof>
	<crc></crc>
	<manufacturer></manufacturer>
	<year></year>
	<genre></genre>
	<rating></rating>
	<enabled>Yes</enabled>
</game>
<game name="Las Vegas (Bandai, LCD Game Digital)" index="true" image="l">
	<description>Las Vegas (Bandai, LCD Game Digital)</description>
	<cloneof></cloneof>
	<crc></crc>
	<manufacturer></manufacturer>
	<year></year>
	<genre></genre>
	<rating></rating>
	<enabled>Yes</enabled>
</game>
<game name="Lifeboat (Nintendo, Multi Screen)" index="" image="">
	<description>Lifeboat (Nintendo, Multi Screen)</description>
	<cloneof></cloneof>
	<crc></crc>
	<manufacturer></manufacturer>
	<year></year>
	<genre></genre>
	<rating></rating>
	<enabled>Yes</enabled>
</game>
<game name="Mario Bros. (Nintendo, Multi Screen)" index="true" image="m">
	<description>Mario Bros. (Nintendo, Multi Screen)</description>
	<cloneof></cloneof>
	<crc></crc>
	<manufacturer></manufacturer>
	<year></year>
	<genre></genre>
	<rating></rating>
	<enabled>Yes</enabled>
</game>
<game name="Mickey Mouse (Nintendo, Panorama Screen)" index="" image="">
	<description>Mickey Mouse (Nintendo, Panorama Screen)</description>
	<cloneof></cloneof>
	<crc></crc>
	<manufacturer></manufacturer>
	<year></year>
	<genre></genre>
	<rating></rating>
	<enabled>Yes</enabled>
</game>
<game name="Mickey Mouse (Nintendo, Wide Screen)" index="" image="">
	<description>Mickey Mouse (Nintendo, Wide Screen)</description>
	<cloneof></cloneof>
	<crc></crc>
	<manufacturer></manufacturer>
	<year></year>
	<genre></genre>
	<rating></rating>
	<enabled>Yes</enabled>
</game>
<game name="Monkey (VTech, Time &amp; Fun)" index="" image="">
	<description>Monkey (VTech, Time &amp; Fun)</description>
	<cloneof></cloneof>
	<crc></crc>
	<manufacturer></manufacturer>
	<year></year>
	<genre></genre>
	<rating></rating>
	<enabled>Yes</enabled>
</game>
<game name="Monkey Jump (VTech, Arcade Time &amp; Fun)" index="" image="">
	<description>Monkey Jump (VTech, Arcade Time &amp; Fun)</description>
	<cloneof></cloneof>
	<crc></crc>
	<manufacturer></manufacturer>
	<year></year>
	<genre></genre>
	<rating></rating>
	<enabled>Yes</enabled>
</game>
<game name="Motor Cross (Queentex)" index="" image="">
	<description>Motor Cross (Queentex)</description>
	<cloneof></cloneof>
	<crc></crc>
	<manufacturer></manufacturer>
	<year></year>
	<genre></genre>
	<rating></rating>
	<enabled>Yes</enabled>
</game>
<game name="Pac Man (Tomytronic)" index="true" image="p">
	<description>Pac Man (Tomytronic)</description>
	<cloneof></cloneof>
	<crc></crc>
	<manufacturer></manufacturer>
	<year></year>
	<genre></genre>
	<rating></rating>
	<enabled>Yes</enabled>
</game>
<game name="Pancake (VTech, Time &amp; Fun)" index="" image="">
	<description>Pancake (VTech, Time &amp; Fun)</description>
	<cloneof></cloneof>
	<crc></crc>
	<manufacturer></manufacturer>
	<year></year>
	<genre></genre>
	<rating></rating>
	<enabled>Yes</enabled>
</game>
<game name="Parachute (Nintendo, Wide Screen)" index="" image="">
	<description>Parachute (Nintendo, Wide Screen)</description>
	<cloneof></cloneof>
	<crc></crc>
	<manufacturer></manufacturer>
	<year></year>
	<genre></genre>
	<rating></rating>
	<enabled>Yes</enabled>
</game>
<game name="Pirate (VTech, Time &amp; Fun)" index="" image="">
	<description>Pirate (VTech, Time &amp; Fun)</description>
	<cloneof></cloneof>
	<crc></crc>
	<manufacturer></manufacturer>
	<year></year>
	<genre></genre>
	<rating></rating>
	<enabled>Yes</enabled>
</game>
<game name="Roller Coaster (VTech, Explorer Time &amp; Fun)" index="true" image="r">
	<description>Roller Coaster (VTech, Explorer Time &amp; Fun)</description>
	<cloneof></cloneof>
	<crc></crc>
	<manufacturer></manufacturer>
	<year></year>
	<genre></genre>
	<rating></rating>
	<enabled>Yes</enabled>
</game>
<game name="Safari (VTech, Time &amp; Fun)" index="true" image="s">
	<description>Safari (VTech, Time &amp; Fun)</description>
	<cloneof></cloneof>
	<crc></crc>
	<manufacturer></manufacturer>
	<year></year>
	<genre></genre>
	<rating></rating>
	<enabled>Yes</enabled>
</game>
<game name="Sleep Walker (VTech, Time &amp; Fun)" index="" image="">
	<description>Sleep Walker (VTech, Time &amp; Fun)</description>
	<cloneof></cloneof>
	<crc></crc>
	<manufacturer></manufacturer>
	<year></year>
	<genre></genre>
	<rating></rating>
	<enabled>Yes</enabled>
</game>
<game name="Snoopy (Nintendo, Table Top)" index="" image="">
	<description>Snoopy (Nintendo, Table Top)</description>
	<cloneof></cloneof>
	<crc></crc>
	<manufacturer></manufacturer>
	<year></year>
	<genre></genre>
	<rating></rating>
	<enabled>Yes</enabled>
</game>
<game name="Snoopy Tennis (Nintendo, Wide Screen)" index="" image="">
	<description>Snoopy Tennis (Nintendo, Wide Screen)</description>
	<cloneof></cloneof>
	<crc></crc>
	<manufacturer></manufacturer>
	<year></year>
	<genre></genre>
	<rating></rating>
	<enabled>Yes</enabled>
</game>
<game name="Sub Chase (Mattel Electronics)" index="" image="">
	<description>Sub Chase (Mattel Electronics)</description>
	<cloneof></cloneof>
	<crc></crc>
	<manufacturer></manufacturer>
	<year></year>
	<genre></genre>
	<rating></rating>
	<enabled>Yes</enabled>
</game>
<game name="Tennis Menace (VTech, Sporty Time &amp; Fun)" index="true" image="t">
	<description>Tennis Menace (VTech, Sporty Time &amp; Fun)</description>
	<cloneof></cloneof>
	<crc></crc>
	<manufacturer></manufacturer>
	<year></year>
	<genre></genre>
	<rating></rating>
	<enabled>Yes</enabled>
</game>
<game name="Towering Rescue (Gakken, LCD Card Game)" index="" image="">
	<description>Towering Rescue (Gakken, LCD Card Game)</description>
	<cloneof></cloneof>
	<crc></crc>
	<manufacturer></manufacturer>
	<year></year>
	<genre></genre>
	<rating></rating>
	<enabled>Yes</enabled>
</game>
<game name="Tron (Tomytronic)" index="" image="">
	<description>Tron (Tomytronic)</description>
	<cloneof></cloneof>
	<crc></crc>
	<manufacturer></manufacturer>
	<year></year>
	<genre></genre>
	<rating></rating>
	<enabled>Yes</enabled>
</game>
<game name="Turtle Bridge (Nintendo, Wide Screen)" index="" image="">
	<description>Turtle Bridge (Nintendo, Wide Screen)</description>
	<cloneof></cloneof>
	<crc></crc>
	<manufacturer></manufacturer>
	<year></year>
	<genre></genre>
	<rating></rating>
	<enabled>Yes</enabled>
</game>
<game name="Wild Man Jump (VTech, Electronic Tini-Arcade)" index="true" image="w">
	<description>Wild Man Jump (VTech, Electronic Tini-Arcade)</description>
	<cloneof></cloneof>
	<crc></crc>
	<manufacturer></manufacturer>
	<year></year>
	<genre></genre>
	<rating></rating>
	<enabled>Yes</enabled>
</game>
</menu>
